acs/__init__.py
acs/metric.py
acs/utils.py
acs/components/__init__.py
acs/components/cognitive_load.py
acs/components/inclusive_language.py
acs/components/plain_language.py
acs/components/structure.py
acs_metric-0.1.0.dist-info/licenses/LICENSE
acs_metric-0.1.0.dist-info/METADATA
acs_metric-0.1.0.dist-info/WHEEL
acs_metric-0.1.0.dist-info/top_level.txt
acs_metric-0.1.0.dist-info/RECORD
